verbosity/__init__.py
verbosity/verbosity.py
verbosity-0.1.dist-info/DESCRIPTION.rst
verbosity-0.1.dist-info/METADATA
verbosity-0.1.dist-info/RECORD
verbosity-0.1.dist-info/WHEEL
verbosity-0.1.dist-info/metadata.json
verbosity-0.1.dist-info/top_level.txt
