Metadata-Version: 2.0
Name: verbosity
Version: 0.1
Summary: Add verbosity options with argparse and logging
Home-page: https://github.com/jspv/verbosity
Author: Justin S. Peavey
Author-email: jspvpypi@twinleaf.xyz
License: UNKNOWN
Download-URL: https://github.com/jspv/verbosity/archive/0.1.tar.gz
Keywords: argparse,logging
Platform: UNKNOWN
Classifier: Development Status :: 3 - Alpha
Classifier: Intended Audience :: Developers
Classifier: Topic :: Software Development :: Build Tools
Classifier: License :: OSI Approved :: MIT License
Classifier: Programming Language :: Python :: 3
Requires-Python: >=3
